myanmar_gpt/__init__.py
myanmar_gpt-0.0.1.dist-info/LICENSE
myanmar_gpt-0.0.1.dist-info/METADATA
myanmar_gpt-0.0.1.dist-info/WHEEL
myanmar_gpt-0.0.1.dist-info/top_level.txt
myanmar_gpt-0.0.1.dist-info/RECORD
